odoo/addons/website_event_sale_b2x_alt_price/README.rst
odoo/addons/website_event_sale_b2x_alt_price/__init__.py
odoo/addons/website_event_sale_b2x_alt_price/__manifest__.py
odoo/addons/website_event_sale_b2x_alt_price/i18n/es.po
odoo/addons/website_event_sale_b2x_alt_price/i18n/it.po
odoo/addons/website_event_sale_b2x_alt_price/i18n/website_event_sale_b2x_alt_price.pot
odoo/addons/website_event_sale_b2x_alt_price/models/__init__.py
odoo/addons/website_event_sale_b2x_alt_price/models/event_ticket.py
odoo/addons/website_event_sale_b2x_alt_price/readme/CONTRIBUTORS.md
odoo/addons/website_event_sale_b2x_alt_price/readme/DESCRIPTION.md
odoo/addons/website_event_sale_b2x_alt_price/readme/USAGE.md
odoo/addons/website_event_sale_b2x_alt_price/static/description/icon.png
odoo/addons/website_event_sale_b2x_alt_price/static/description/index.html
odoo/addons/website_event_sale_b2x_alt_price/static/src/js/b2b.esm.js
odoo/addons/website_event_sale_b2x_alt_price/static/src/js/b2b_with_discount.esm.js
odoo/addons/website_event_sale_b2x_alt_price/static/src/js/b2c.esm.js
odoo/addons/website_event_sale_b2x_alt_price/static/src/js/b2c_with_discount.esm.js
odoo/addons/website_event_sale_b2x_alt_price/static/src/scss/website_event.scss
odoo/addons/website_event_sale_b2x_alt_price/templates/website_event_sale.xml
odoo/addons/website_event_sale_b2x_alt_price/tests/__init__.py
odoo/addons/website_event_sale_b2x_alt_price/tests/test_ui.py
odoo_addon_website_event_sale_b2x_alt_price-17.0.1.0.0.2.dist-info/METADATA
odoo_addon_website_event_sale_b2x_alt_price-17.0.1.0.0.2.dist-info/WHEEL
odoo_addon_website_event_sale_b2x_alt_price-17.0.1.0.0.2.dist-info/top_level.txt
odoo_addon_website_event_sale_b2x_alt_price-17.0.1.0.0.2.dist-info/RECORD
